CHANGES.rst
CONTRIBUTORS.rst
COPYING.LGPLv3
MANIFEST.in
README.rst
setup.py
django_inlinetrans.egg-info/PKG-INFO
django_inlinetrans.egg-info/SOURCES.txt
django_inlinetrans.egg-info/dependency_links.txt
django_inlinetrans.egg-info/requires.txt
django_inlinetrans.egg-info/top_level.txt
inlinetrans/__init__.py
inlinetrans/settings.py
inlinetrans/urls.py
inlinetrans/utils.py
inlinetrans/views.py
inlinetrans/locale/es/LC_MESSAGES/django.mo
inlinetrans/locale/es/LC_MESSAGES/django.po
inlinetrans/management/__init__.py
inlinetrans/management/commands/__init__.py
inlinetrans/management/commands/inline_makemessages.py
inlinetrans/static/inlinetrans/css/inlinetrans.css
inlinetrans/static/inlinetrans/img/ajax-loader-transparent.gif
inlinetrans/static/inlinetrans/js/jquery.inlinetrans.js
inlinetrans/templates/inlinetrans/inc.csrf_token.html
inlinetrans/templates/inlinetrans/inline_header.html
inlinetrans/templates/inlinetrans/inline_toolbar.html
inlinetrans/templates/inlinetrans/inline_trans.html
inlinetrans/templates/inlinetrans/response.html
inlinetrans/templatetags/__init__.py
inlinetrans/templatetags/inlinetrans.py