Metadata-Version: 1.1
Name: django-inlinetrans
Version: 0.6.0
Summary: Is a django application that allows the translation of django templtes from the rendered html in the browser
Home-page: https://github.com/Yaco-Sistemas/django-inlinetrans
Author: Antonio Pérez-Aranda Alcaide
Author-email: ant30tx@gmail.com
License: LGPL 3
Keywords: django translation,django,translation,inline
Platform: UNKNOWN
Classifier: Development Status :: 4 - Beta
Classifier: Framework :: Django
Classifier: License :: OSI Approved :: GNU Library or Lesser General Public License (LGPL)
Classifier: Programming Language :: Python :: 2
Classifier: Programming Language :: Python :: 3
